Metadata-Version: 2.1
Name: searchdups
Version: 1.0.0
Summary: Searches for duplicate files in folders (recursively, if needed)
Home-page: https://github.com/dealfonso/searchdups
Author: Carlos A.
Author-email: caralla@upv.es
License: Apache 2.0
Keywords: command line,cli,files,sysadmin
Classifier: Development Status :: 4 - Beta
Classifier: Topic :: Utilities
Classifier: License :: OSI Approved :: Apache Software License
Classifier: Programming Language :: Python :: 3
License-File: LICENSE
